con_ACP/__init__.py
con_ACP/inf.py
con_ACP/model/ResNet.py
con_ACP/model/__init__.py
con_ACP/model/attention_encoder.py
con_ACP/model/cnn.py
con_ACP/model/lstm.py
con_ACP/model_old/ResNet.py
con_ACP/model_old/__init__.py
con_ACP/model_old/attention_encoder.py
con_ACP/model_old/cnn.py
con_ACP/model_old/lstm.py
funcpeppred-0.0.3.dist-info/METADATA
funcpeppred-0.0.3.dist-info/WHEEL
funcpeppred-0.0.3.dist-info/top_level.txt
funcpeppred-0.0.3.dist-info/RECORD
