Metadata-Version: 2.1
Name: funcpeppred
Version: 0.0.3
Summary: Screening anticancer peptide from amino acid sequence data
Home-page: https://github.com/bzlee-bio/con_ACP
Author: Byungjo Lee
Author-email: blee.inf@gmail.com
Keywords: anticancer peptide,sequence data,deep learning
Classifier: Programming Language :: Python :: 3.6
Classifier: Programming Language :: Python :: 3.7
Classifier: Programming Language :: Python :: 3.8
Classifier: Programming Language :: Python :: 3.9
Requires-Python: >=3.6
Requires-Dist: torch
